{"0.0.0":{"items":{"block":["cubyz:baobab_branch"]},"obj":{"texture1":"cubyz:branch/baobab/half_line","friction":20,"absorbedLight":2107440,"rotation":"cubyz:branch","texture2":"cubyz:branch/baobab/line","selectable":true,"mobility":1,"collide":true,"transparent":false,"model":{"radius":4},"lodReplacement":"cubyz:baobab_branch","bounciness":0,"blockHealth":4,"texture4":"cubyz:branch/baobab/intersection","opaqueVariant":"cubyz:baobab_branch","texture5":"cubyz:branch/baobab/cross","drops":[{"chance":1,"items":[{"item":"cubyz:baobab_branch","amount":1}]}],"hasBackFace":false,"hasItem":true,"emittedLight":0,"degradable":false,"replacable":false,"viewThrough":false,"texture0":"cubyz:branch/baobab/dot","terminalVelocity":90,"item":{"food":0,"texture":"branch/baobab.png","block":"cubyz:baobab_branch","name":"cubyz:baobab_branch","material":{"durability":20,"textureRoughness":0.7000000000000001,"massDamage":0.4,"swingSpeed":6.3,"modifiers":[{"id":"fragile","strength":0.1}],"colors":[4283515960,4284895301,4286209357,4287852892,4286209357],"hardnessDamage":0.4},"stacksize":120},"tags":["choppable","wood"],"allowOres":false,"texture3":"cubyz:branch/baobab/bend","blockResistance":0,"alwaysViewThrough":false,"density":0.001},"blocks":{"lodReplacement":["cubyz:baobab_branch"],"opaqueVariant":["cubyz:baobab_branch"]}}}