{"0.0.0":{"items":{"block":["cubyz:water"]},"obj":{"friction":20,"absorbedLight":591105,"selectable":false,"rotation":"cubyz:no_rotation","mobility":0.6000000000000001,"collide":false,"transparent":true,"model":"cubyz:cube","lodReplacement":"cubyz:water","bounciness":0,"blockHealth":1,"opaqueVariant":"cubyz:water","drops":[],"hasBackFace":true,"hasItem":true,"texture":"cubyz:water","degradable":true,"emittedLight":0,"replacable":true,"viewThrough":true,"terminalVelocity":5,"tags":["fluid"],"allowOres":false,"blockResistance":0,"alwaysViewThrough":false,"density":0.998},"blocks":{"lodReplacement":["cubyz:water"],"opaqueVariant":["cubyz:water"]}}}